setup.cfg
setup.py
kraconvert/__init__.py
kraconvert/__main__.py
kraconvert/kra.py
kraconvert/main.py
kraconvert/utils.py
kraconvert.egg-info/PKG-INFO
kraconvert.egg-info/SOURCES.txt
kraconvert.egg-info/dependency_links.txt
kraconvert.egg-info/entry_points.txt
kraconvert.egg-info/pbr.json
kraconvert.egg-info/requires.txt
kraconvert.egg-info/top_level.txt
kraconvert/files/sRGB.icc