Metadata-Version: 1.1
Name: kraconvert
Version: 0.2
Summary: Konverts Krita .kra files into PNG and JPEG.
Home-page: https://github.com/bloodywing/kraconvert
Author: Pierre Geier <bloodywing>
Author-email: pierre@isartistic.biz
License: CC0
Download-URL: https://github.com/bloodywing/kraconvert/tarball/0.2
Keywords: experimental,krita,converter,tool,utility
Platform: UNKNOWN
Classifier: License :: CC0 1.0 Universal (CC0 1.0) Public Domain Dedication
Classifier: Intended Audience :: End Users/Desktop
Classifier: Programming Language :: Python :: 3
Classifier: Topic :: Artistic Software
Classifier: Topic :: Multimedia :: Graphics :: Graphics Conversion
Classifier: Topic :: Utilities
